pywormholescan/.DS_Store
pywormholescan/__init__.py
pywormholescan/_internal/__init__.py
pywormholescan/_internal/api_client.py
pywormholescan/_internal/network.py
pywormholescan/_internal/url_builder.py
pywormholescan/guardian.py
pywormholescan/wormholescan.py
pywormholescan-0.1.2.dist-info/LICENSE
pywormholescan-0.1.2.dist-info/METADATA
pywormholescan-0.1.2.dist-info/WHEEL
pywormholescan-0.1.2.dist-info/RECORD
